[
  {
    "id": 1,
    "status": 200,
    "title": "MODX",
    "headings": [
      "Обзор ресурса (1)",
      "Общие",
      "Просмотр дочерних ресурсов"
    ],
    "labels": [
      "Пожалуйста, подождите...",
      "Общие",
      "Заголовок:",
      "Главная",
      "Расширенный заголовок:",
      "(нет данных)",
      "Описание:",
      "(нет данных)",
      "Аннотация (введение):",
      "(нет данных)",
      "Тип:",
      "Ресурс",
      "Псевдоним:",
      "index",
      "Создание и изменение",
      "Создан:",
      "26-10-2005 09:32:01 (SVadmin)",
      "Редактировался:",
      "12-07-2026 09:09:47 (SVadmin)",
      "Статус",
      "Статус:",
      "Опубликован",
      "Дата публикации:",
      "(нет данных)",
      "Дата отмены публикации:",
      "(нет данных)",
      "Кэшируемый:",
      "Да",
      "Доступен для поиска:",
      "Да",
      "Позиция в меню:",
      "0",
      "Показывать в меню:",
      "Нет",
      "Веб-доступ:",
      "Доступен для всех",
      "Менеджерский доступ:",
      "Доступен для всех",
      "Разметка/структура",
      "Шаблон:",
      "Главная",
      "Использовать HTML-редактор:",
      "Да",
      "Ресурс является контейнером:",
      "Да",
      "1726",
      "Новый ресурс",
      "09-04-2020",
      "09-04-2020",
      "Опубликован",
      "1725",
      "ччч",
      "09-04-2020",
      "09-04-2020",
      "Опубликован",
      "1719",
      "ИИ",
      "02-04-2020",
      "02-04-2020",
      "Опубликован",
      "1718",
      "ПРЯМАЯ ТРАНСЛЯЦИЯ БОГОСЛУЖЕНИЙ",
      "02-04-2020",
      "02-04-2020",
      "Опубликован"
    ],
    "fields": [
      {
        "name": "sort",
        "type": "select-one",
        "value": "createdon",
        "checked": false,
        "options": [
          "Дата создания"
        ]
      },
      {
        "name": "dir",
        "type": "select-one",
        "value": "DESC",
        "checked": false,
        "options": [
          "По убыванию"
        ]
      }
    ]
  },
  {
    "id": 14,
    "status": 200,
    "title": "MODX",
    "headings": [
      "Обзор ресурса (14)",
      "Общие",
      "Просмотр дочерних ресурсов"
    ],
    "labels": [
      "Пожалуйста, подождите...",
      "Общие",
      "Заголовок:",
      "Расписание богослужений",
      "Расширенный заголовок:",
      "(нет данных)",
      "Описание:",
      "(нет данных)",
      "Аннотация (введение):",
      "(нет данных)",
      "Тип:",
      "Ресурс",
      "Псевдоним:",
      "raspisanie-bogosluzheniy",
      "Создание и изменение",
      "Создан:",
      "04-03-2014 11:07:30 (SVadmin)",
      "Редактировался:",
      "30-06-2026 19:19:16 (SVadmin)",
      "Статус",
      "Статус:",
      "Опубликован",
      "Дата публикации:",
      "(нет данных)",
      "Дата отмены публикации:",
      "(нет данных)",
      "Кэшируемый:",
      "Да",
      "Доступен для поиска:",
      "Да",
      "Позиция в меню:",
      "7",
      "Показывать в меню:",
      "Да",
      "Веб-доступ:",
      "Доступен для всех",
      "Менеджерский доступ:",
      "Доступен для всех",
      "Разметка/структура",
      "Шаблон:",
      "Внутренняя",
      "Использовать HTML-редактор:",
      "Да",
      "Ресурс является контейнером:",
      "Нет"
    ],
    "fields": []
  },
  {
    "id": 20,
    "status": 200,
    "title": "MODX",
    "headings": [
      "Обзор ресурса (20)",
      "Общие",
      "Просмотр дочерних ресурсов"
    ],
    "labels": [
      "Пожалуйста, подождите...",
      "Общие",
      "Заголовок:",
      "Приходской листок",
      "Расширенный заголовок:",
      "(нет данных)",
      "Описание:",
      "(нет данных)",
      "Аннотация (введение):",
      "(нет данных)",
      "Тип:",
      "Ресурс",
      "Псевдоним:",
      "prihodskoy-listok",
      "Создание и изменение",
      "Создан:",
      "04-03-2014 15:46:13 (SVadmin)",
      "Редактировался:",
      "29-05-2026 12:12:43 (SVadmin)",
      "Статус",
      "Статус:",
      "Опубликован",
      "Дата публикации:",
      "01-01-2004 20:41:00",
      "Дата отмены публикации:",
      "(нет данных)",
      "Кэшируемый:",
      "Да",
      "Доступен для поиска:",
      "Да",
      "Позиция в меню:",
      "2",
      "Показывать в меню:",
      "Да",
      "Веб-доступ:",
      "Доступен для всех",
      "Менеджерский доступ:",
      "Доступен для всех",
      "Разметка/структура",
      "Шаблон:",
      "Приходской листок(страница)",
      "Использовать HTML-редактор:",
      "Да",
      "Ресурс является контейнером:",
      "Да",
      "2436",
      "2026",
      "06-01-2026",
      "Опубликован",
      "2435",
      "2025",
      "18-04-2025",
      "Опубликован",
      "2246",
      "2024",
      "06-01-2024",
      "Опубликован",
      "2110",
      "2023",
      "31-12-2022",
      "Опубликован",
      "1868",
      "2022",
      "04-01-2022",
      "Опубликован",
      "1776",
      "2021",
      "06-01-2021",
      "Опубликован",
      "1648",
      "2020",
      "03-01-2020",
      "03-01-2020",
      "Опубликован",
      "1457",
      "2019",
      "06-01-2019",
      "06-01-2019",
      "Опубликован",
      "1285",
      "2018",
      "31-12-2017",
      "Опубликован",
      "1095",
      "2017",
      "31-12-2016",
      "Опубликован",
      "879",
      "2016",
      "29-12-2015",
      "Опубликован",
      "549",
      "2015",
      "04-01-2015",
      "Опубликован",
      "373",
      "2006",
      "28-06-2014",
      "28-06-2014",
      "Опубликован",
      "348",
      "2009",
      "03-06-2014",
      "03-06-2014",
      "Опубликован",
      "345",
      "2010",
      "31-05-2014",
      "31-05-2014",
      "Опубликован",
      "343",
      "Duplicate of 2011",
      "31-05-2014",
      "Не опубликован",
      "147",
      "2011",
      "07-04-2014",
      "Опубликован",
      "134",
      "2012",
      "03-04-2014",
      "Опубликован",
      "132",
      "2013",
      "01-04-2014",
      "01-01-2013",
      "Опубликован",
      "131",
      "2014",
      "01-04-2014",
      "01-01-2014",
      "Опубликован"
    ],
    "fields": [
      {
        "name": "sort",
        "type": "select-one",
        "value": "createdon",
        "checked": false,
        "options": [
          "Дата создания"
        ]
      },
      {
        "name": "dir",
        "type": "select-one",
        "value": "DESC",
        "checked": false,
        "options": [
          "По убыванию"
        ]
      }
    ]
  },
  {
    "id": 48,
    "status": 200,
    "title": "MODX",
    "headings": [
      "Обзор ресурса (48)",
      "Общие",
      "Просмотр дочерних ресурсов"
    ],
    "labels": [
      "Пожалуйста, подождите...",
      "Общие",
      "Заголовок:",
      "Расписание занятий",
      "Расширенный заголовок:",
      "(нет данных)",
      "Описание:",
      "(нет данных)",
      "Аннотация (введение):",
      "(нет данных)",
      "Тип:",
      "Ресурс",
      "Псевдоним:",
      "raspisanie-zanyatiy",
      "Создание и изменение",
      "Создан:",
      "12-03-2014 11:13:31 (SVadmin)",
      "Редактировался:",
      "10-08-2025 15:49:47 (SVadmin)",
      "Статус",
      "Статус:",
      "Опубликован",
      "Дата публикации:",
      "12-03-2014 11:13:21",
      "Дата отмены публикации:",
      "(нет данных)",
      "Кэшируемый:",
      "Да",
      "Доступен для поиска:",
      "Да",
      "Позиция в меню:",
      "3",
      "Показывать в меню:",
      "Да",
      "Веб-доступ:",
      "Доступен для всех",
      "Менеджерский доступ:",
      "Доступен для всех",
      "Разметка/структура",
      "Шаблон:",
      "Внутренняя",
      "Использовать HTML-редактор:",
      "Да",
      "Ресурс является контейнером:",
      "Нет"
    ],
    "fields": []
  },
  {
    "id": 2436,
    "status": 200,
    "title": "MODX",
    "headings": [
      "Обзор ресурса (2436)",
      "Общие",
      "Просмотр дочерних ресурсов"
    ],
    "labels": [
      "Пожалуйста, подождите...",
      "Общие",
      "Заголовок:",
      "2026",
      "Расширенный заголовок:",
      "(нет данных)",
      "Описание:",
      "(нет данных)",
      "Аннотация (введение):",
      "(нет данных)",
      "Тип:",
      "Ресурс",
      "Псевдоним:",
      "2026",
      "Создание и изменение",
      "Создан:",
      "06-01-2026 12:11:15 (SVadmin)",
      "Редактировался:",
      "29-05-2026 12:12:01 (SVadmin)",
      "Статус",
      "Статус:",
      "Опубликован",
      "Дата публикации:",
      "(нет данных)",
      "Дата отмены публикации:",
      "(нет данных)",
      "Кэшируемый:",
      "Да",
      "Доступен для поиска:",
      "Да",
      "Позиция в меню:",
      "21",
      "Показывать в меню:",
      "Да",
      "Веб-доступ:",
      "Доступен для всех",
      "Менеджерский доступ:",
      "Доступен для всех",
      "Разметка/структура",
      "Шаблон:",
      "Приходской листок",
      "Использовать HTML-редактор:",
      "Да",
      "Ресурс является контейнером:",
      "Нет"
    ],
    "fields": []
  }
]